django_async_manager/__init__.py
django_async_manager/apps.py
django_async_manager/asgi.py
django_async_manager/decorators.py
django_async_manager/models.py
django_async_manager/scheduler.py
django_async_manager/settings.py
django_async_manager/urls.py
django_async_manager/utils.py
django_async_manager/worker.py
django_async_manager/wsgi.py
django_async_manager/management/__init__.py
django_async_manager/management/commands/__init__.py
django_async_manager/management/commands/run_scheduler.py
django_async_manager/management/commands/run_worker.py
django_async_manager/management/commands/update_beat_schedule.py
django_async_manager/migrations/0001_initial.py
django_async_manager/migrations/0002_task_django_asyn_queue_de1c17_idx.py
django_async_manager/migrations/0003_task_memory_limit.py
django_async_manager/migrations/__init__.py
django_async_manager/tests/__init__.py
django_async_manager/tests/factories.py
django_async_manager/tests/test_decorator.py
django_async_manager/tests/test_memory_management.py
django_async_manager/tests/test_run_scheduler.py
django_async_manager/tests/test_run_worker.py
django_async_manager/tests/test_scheduler.py
django_async_manager/tests/test_update_beat_schedule.py
django_async_manager/tests/test_utils.py
django_async_manager/tests/test_worker.py
django_async_manager/tests/test_models/__init__.py
django_async_manager/tests/test_models/test_crontab_schedule.py
django_async_manager/tests/test_models/test_periodic_task.py
django_async_manager/tests/test_models/test_task.py
django_async_manager-0.2.0.dist-info/licenses/LICENSE
django_async_manager-0.2.0.dist-info/METADATA
django_async_manager-0.2.0.dist-info/WHEEL
django_async_manager-0.2.0.dist-info/top_level.txt
django_async_manager-0.2.0.dist-info/RECORD
