Metadata-Version: 2.4
Name: django-async-manager
Version: 0.2.0
Summary: Django library for managing asynchronous tasks with scheduling and dependency management
Author-email: Michał Konwiak <michalkonwiak1@gmail.com>
License: MIT
Project-URL: Homepage, https://github.com/michalkonwiak/django-async-manager
Project-URL: Documentation, https://github.com/michalkonwiak/django-async-manager
Project-URL: Repository, https://github.com/michalkonwiak/django-async-manager.git
Project-URL: Issues, https://github.com/michalkonwiak/django-async-manager/issues
Classifier: Development Status :: 4 - Beta
Classifier: Environment :: Web Environment
Classifier: Framework :: Django
Classifier: Framework :: Django :: 4.2
Classifier: Intended Audience :: Developers
Classifier: License :: OSI Approved :: MIT License
Classifier: Operating System :: OS Independent
Classifier: Programming Language :: Python
Classifier: Programming Language :: Python :: 3
Classifier: Programming Language :: Python :: 3.12
Classifier: Topic :: Software Development :: Libraries :: Python Modules
Requires-Python: >=3.12
License-File: LICENSE
Requires-Dist: croniter>=6.0.0
Requires-Dist: django>=3.2
Requires-Dist: psutil>=5.9.0
Provides-Extra: dev
Requires-Dist: coverage>=7.8.0; extra == "dev"
Requires-Dist: django-stubs>=5.1.3; extra == "dev"
Requires-Dist: factory-boy>=3.3.3; extra == "dev"
Requires-Dist: flake8>=7.1.2; extra == "dev"
Requires-Dist: pre-commit>=4.1.0; extra == "dev"
Requires-Dist: pytest>=8.3.5; extra == "dev"
Requires-Dist: pytest-django>=4.10.0; extra == "dev"
Requires-Dist: ruff>=0.9.10; extra == "dev"
Dynamic: license-file
